.copier-answers.yml
.gitignore
.gitlab-ci.yml
CHANGELOG.md
LICENSE
PKG-INFO
README.md
pyproject.toml
.git_hooks/post-commit
.git_hooks/pre-commit
.github/workflows/ci.yml
.github/workflows/semantic_release.yml
bec_testing_plugin/__init__.py
bec_testing_plugin/bec_ipython_client/__init__.py
bec_testing_plugin/bec_ipython_client/high_level_interface/__init__.py
bec_testing_plugin/bec_ipython_client/startup/__init__.py
bec_testing_plugin/bec_ipython_client/startup/post_startup.py
bec_testing_plugin/bec_ipython_client/startup/pre_startup.py
bec_testing_plugin/bec_widgets/__init__.py
bec_testing_plugin/bec_widgets/auto_updates/__init__.py
bec_testing_plugin/bec_widgets/widgets/__init__.py
bec_testing_plugin/bec_widgets/widgets/client.py
bec_testing_plugin/bec_widgets/widgets/ExampleWidgetPlugin/ExampleWidgetPlugin.py
bec_testing_plugin/bec_widgets/widgets/ExampleWidgetPlugin/ExampleWidgetPlugin.ui
bec_testing_plugin/bec_widgets/widgets/ExampleWidgetPlugin/ExampleWidgetPlugin_ui.py
bec_testing_plugin/bec_widgets/widgets/ExampleWidgetPlugin/__init__.py
bec_testing_plugin/bec_widgets/widgets/NoUiWidgetPlugin/NoUiWidgetPlugin.py
bec_testing_plugin/bec_widgets/widgets/NoUiWidgetPlugin/__init__.py
bec_testing_plugin/deployments/__init__.py
bec_testing_plugin/deployments/device_server/__init__.py
bec_testing_plugin/deployments/device_server/startup.py
bec_testing_plugin/device_configs/__init__.py
bec_testing_plugin/devices/__init__.py
bec_testing_plugin/file_writer/__init__.py
bec_testing_plugin/macros/README.md
bec_testing_plugin/macros/__init__.py
bec_testing_plugin/macros/macro_test.py
bec_testing_plugin/scans/__init__.py
bec_testing_plugin/scans/custom_scan.py
bec_testing_plugin/scans/device_progress_scan.py
bec_testing_plugin/scans/metadata_schema/__init__.py
bec_testing_plugin/scans/metadata_schema/custom_test_scan_schema.py
bec_testing_plugin/scans/metadata_schema/metadata_schema_registry.py
bec_testing_plugin/scans/metadata_schema/metadata_schema_template.py
bec_testing_plugin-0.3.0.dist-info/METADATA
bec_testing_plugin-0.3.0.dist-info/WHEEL
bec_testing_plugin-0.3.0.dist-info/entry_points.txt
bec_testing_plugin-0.3.0.dist-info/licenses/LICENSE
bec_testing_plugin-0.3.0.dist-info/RECORD
