Metadata-Version: 2.4
Name: bec_testing_plugin
Version: 0.3.0
Summary: A plugin repository for BEC
License-File: LICENSE
Classifier: Development Status :: 3 - Alpha
Classifier: Programming Language :: Python :: 3
Classifier: Topic :: Scientific/Engineering
Requires-Python: >=3.10
Provides-Extra: dev
Requires-Dist: bec-server; extra == 'dev'
Requires-Dist: black; extra == 'dev'
Requires-Dist: copier; extra == 'dev'
Requires-Dist: coverage; extra == 'dev'
Requires-Dist: isort; extra == 'dev'
Requires-Dist: ophyd-devices; extra == 'dev'
Requires-Dist: pylint; extra == 'dev'
Requires-Dist: pytest; extra == 'dev'
Requires-Dist: pytest-random-order; extra == 'dev'
